ofpubsub/__init__.py
ofpubsub-0.7.dist-info/DESCRIPTION.rst
ofpubsub-0.7.dist-info/METADATA
ofpubsub-0.7.dist-info/RECORD
ofpubsub-0.7.dist-info/WHEEL
ofpubsub-0.7.dist-info/metadata.json
ofpubsub-0.7.dist-info/top_level.txt
only-pubsub/__init__.py
