Metadata-Version: 2.0
Name: ofpubsub
Version: 0.7
Summary: OnlyFunction PubSub
Home-page: https://github.com/mejik/ofpubsub
Author: Mejik
Author-email: mejik.dev@gmail.com
License: UNKNOWN
Platform: UNKNOWN
Classifier: Programming Language :: Python :: 3
Classifier: License :: OSI Approved :: MIT License
Classifier: Operating System :: OS Independent
Requires-Python: >=3.5
Requires-Dist: requests
